hci_decode_tools/__init__.py
hci_decode_tools/decode.py
hci_decode_tools/sniffer.py
hci_decode_tools/packet_codes/__init__.py
hci_decode_tools/packet_codes/acl.py
hci_decode_tools/packet_codes/att.py
hci_decode_tools/packet_codes/command.py
hci_decode_tools/packet_codes/event.py
hci_decode_tools/packets/__init__.py
hci_decode_tools/packets/_att_packet.py
hci_decode_tools/packets/acl_packet.py
hci_decode_tools/packets/command_packet.py
hci_decode_tools/packets/event_packet.py
hci_decode_tools/utils/__init__.py
hci_decode_tools/utils/params.py
hci_decode_tools/utils/types.py
hci_decode_tools/utils/_packet_structs/__init__.py
hci_decode_tools/utils/_packet_structs/acl_struct.py
hci_decode_tools/utils/_packet_structs/att_struct.py
hci_decode_tools/utils/_packet_structs/command_struct.py
hci_decode_tools/utils/_packet_structs/event_stuct.py
hci_decode_tools_cli.py
max_ble_hci/__init__.py
max_ble_hci/_hci_logger.py
max_ble_hci/_transport.py
max_ble_hci/ad_types.py
max_ble_hci/ble_hci.py
max_ble_hci/ble_standard_cmds.py
max_ble_hci/constants.py
max_ble_hci/data_params.py
max_ble_hci/hci_packets.py
max_ble_hci/packet_codes.py
max_ble_hci/packet_defs.py
max_ble_hci/utils.py
max_ble_hci/vendor_spec_cmds.py
max_ble_hci_cli.py
max_ble_hci-1.4.0.dist-info/METADATA
max_ble_hci-1.4.0.dist-info/WHEEL
max_ble_hci-1.4.0.dist-info/entry_points.txt
max_ble_hci-1.4.0.dist-info/licenses/LICENSE
max_ble_hci-1.4.0.dist-info/RECORD
