Metadata-Version: 2.4
Name: max_ble_hci
Version: 1.4.0
Summary: BLE HCI Test interface for controllers capable of the UART transport
Project-URL: Homepage, https://github.com/Analog-Devices-MSDK/BLE-HCI
Project-URL: Repository, https://github.com/Analog-Devices-MSDK/BLE-HCI
Project-URL: Documentation, https://analog-devices-msdk.github.io/MAX-BLE-HCI/
Project-URL: Bug Tracker, https://github.com/Analog-Devices-MSDK/BLE-HCI/issues
License:                                  Apache License
License-File: LICENSE
Keywords: ble-hci,hci,serial
Classifier: Development Status :: 4 - Beta
Classifier: Programming Language :: Python
Requires-Python: >=3.8
Requires-Dist: alive-progress
Requires-Dist: colorlog
Requires-Dist: gnureadline; platform_system == 'Darwin'
Requires-Dist: pyaes
Requires-Dist: pyreadline3; platform_system == 'Windows'
Requires-Dist: pyserial
